jp2rt/__init__.py
jp2rt/java.py
jp2rt/lib.jar
jp2rt/ml.py
jp2rt/scripts.py
jp2rt-0.2.3.dist-info/METADATA
jp2rt-0.2.3.dist-info/WHEEL
jp2rt-0.2.3.dist-info/entry_points.txt
jp2rt-0.2.3.dist-info/licenses/LICENSE-CC.txt
jp2rt-0.2.3.dist-info/licenses/LICENSE-GPL.txt
jp2rt-0.2.3.dist-info/RECORD
